openoc/__init__.py
openoc/discretization.py
openoc/fastfunc.py
openoc/optimizer.py
openoc/phase.py
openoc/system.py
openoc/variable.py
openoc-0.1.4.dist-info/LICENSE
openoc-0.1.4.dist-info/METADATA
openoc-0.1.4.dist-info/WHEEL
openoc-0.1.4.dist-info/top_level.txt
openoc-0.1.4.dist-info/RECORD
