Metadata-Version: 2.1
Name: openoc
Version: 0.1.4
Summary: free optimal control software
Author-email: Zou Yilin <safe.dust4704@fastmail.com>
Requires-Python: >=3.9
License-File: LICENSE
Requires-Dist: numpy
Requires-Dist: scipy
Requires-Dist: sympy
Requires-Dist: numba
Requires-Dist: cyipopt
Requires-Dist: xxhash
